atl_cache_warmer/ConfluenceSite.py
atl_cache_warmer/JiraSite.py
atl_cache_warmer/__init__.py
atl_cache_warmer/__main__.py
atl_cache_warmer/_utils.py
atl_cache_warmer/cache_builder.py
atl_cache_warmer-0.13.1.dist-info/LICENSE
atl_cache_warmer-0.13.1.dist-info/METADATA
atl_cache_warmer-0.13.1.dist-info/WHEEL
atl_cache_warmer-0.13.1.dist-info/entry_points.txt
atl_cache_warmer-0.13.1.dist-info/top_level.txt
atl_cache_warmer-0.13.1.dist-info/RECORD
