Metadata-Version: 2.1
Name: atl-cache-warmer
Version: 0.13.1
Summary: Little script to warm up confluence and jira caches to make it more responsive
Home-page: https://github.com/np-at/atl_cache_warmer
Author: np-at
Author-email: noahpraskins@gmail.com
License: MIT
Platform: UNKNOWN
Requires-Python: >=3.6
License-File: LICENSE
Requires-Dist: requests
